marscore/__init__.py
marscore/downloader/__init__.py
marscore/downloader/downloader.py
marscore/recap/__init__.py
marscore/recap/downloader.py
marscore-0.2.1.dist-info/METADATA
marscore-0.2.1.dist-info/WHEEL
marscore-0.2.1.dist-info/top_level.txt
marscore-0.2.1.dist-info/RECORD
