Metadata-Version: 2.1
Name: marscore
Version: 0.2.1
Summary: MarsCore (Mars Core) - Developed by Chinese developer Mars (formerly: Ma Yu Chao)，A high-performance, robust download manager built with Python that supports both multi-process，and multi-thread downloading with intelligent error handling and resume capabilities.
Home-page: https://github.com/mars-core/
Author: marscore
Author-email: marcore@126.com
Project-URL: Bug Reports, https://github.com/mars-core/downloder
Project-URL: Source, https://github.com/mars-core/downloder
Keywords: download,multiprocessing,multithreading,dataset
Classifier: Development Status :: 3 - Alpha
Classifier: Intended Audience :: Developers
Classifier: License :: OSI Approved :: MIT License
Classifier: Operating System :: OS Independent
Classifier: Programming Language :: Python :: 3
Classifier: Programming Language :: Python :: 3.6
Classifier: Programming Language :: Python :: 3.7
Classifier: Programming Language :: Python :: 3.8
Classifier: Programming Language :: Python :: 3.9
Classifier: Programming Language :: Python :: 3.10
Requires-Python: >=3.6
Requires-Dist: requests>=2.25.0
Requires-Dist: tqdm>=4.60.0
Requires-Dist: aiohttp>=3.8.0
Requires-Dist: pandas>=1.3.0
Requires-Dist: pyarrow>=5.0.0
